qc_utils/__init__.py
qc_utils/cli.py
qc_utils/commands/__init__.py
qc_utils/commands/clean.py
qc_utils/commands/upload.py
qc_utils/core/__init__.py
qc_utils/core/filters.py
qc_utils/core/gcp_client.py
qc_utils/core/qfield_client.py
digistudio_qc_utils-0.3.0.dist-info/METADATA
digistudio_qc_utils-0.3.0.dist-info/WHEEL
digistudio_qc_utils-0.3.0.dist-info/entry_points.txt
digistudio_qc_utils-0.3.0.dist-info/top_level.txt
digistudio_qc_utils-0.3.0.dist-info/RECORD
