Metadata-Version: 2.4
Name: digistudio-qc-utils
Version: 0.3.0
Summary: CLI utilities for QFieldCloud: upload to GCP, clean old files, and more
Requires-Python: >=3.10
Requires-Dist: qfieldcloud-sdk>=0.11.0
Requires-Dist: google-cloud-storage>=2.10.0
Provides-Extra: dev
Requires-Dist: ruff; extra == "dev"
Requires-Dist: basedpyright; extra == "dev"
